nibabies/__init__.py
nibabies/_types.py
nibabies/_version.py
nibabies/config.py
nibabies/conftest.py
nibabies/cli/__init__.py
nibabies/cli/mcribs.py
nibabies/cli/parser.py
nibabies/cli/run.py
nibabies/cli/version.py
nibabies/cli/workflow.py
nibabies/cli/tests/__init__.py
nibabies/cli/tests/test_parser.py
nibabies/data/FreeSurferLabelRemappings.json
nibabies/data/FreeSurferSubcorticalLabelTableLut.txt
nibabies/data/MNIInfant_to_MNI1526NLinAsym.mat
nibabies/data/__init__.py
nibabies/data/antsBrainExtraction_precise.json
nibabies/data/antsBrainExtraction_testing.json
nibabies/data/boilerplate.bib
nibabies/data/io_spec_anat.json
nibabies/data/io_spec_func.json
nibabies/data/itkIdentityTransform.txt
nibabies/data/reports-spec.yml
nibabies/data/t1-t2-coreg.json
nibabies/data/tpl-MNI152NLin6Asym_res-01_desc-avgwmparc_dseg.nii.gz
nibabies/data/xfm_manifest.json
nibabies/data/flirtsch/bbr.sch
nibabies/data/tests/config.toml
nibabies/interfaces/__init__.py
nibabies/interfaces/bids.py
nibabies/interfaces/confounds.py
nibabies/interfaces/conftest.py
nibabies/interfaces/freesurfer.py
nibabies/interfaces/gifti.py
nibabies/interfaces/maths.py
nibabies/interfaces/mcribs.py
nibabies/interfaces/metric.py
nibabies/interfaces/multiecho.py
nibabies/interfaces/nibabel.py
nibabies/interfaces/patches.py
nibabies/interfaces/reports.py
nibabies/interfaces/resampling.py
nibabies/interfaces/utils.py
nibabies/interfaces/workbench.py
nibabies/interfaces/tests/__init__.py
nibabies/interfaces/tests/test_bids.py
nibabies/interfaces/tests/test_mcribs.py
nibabies/interfaces/tests/test_nibabel.py
nibabies/reports/__init__.py
nibabies/reports/core.py
nibabies/tests/__init__.py
nibabies/tests/test_config.py
nibabies/tests/data/labelfile.txt
nibabies/utils/__init__.py
nibabies/utils/bids.py
nibabies/utils/confounds.py
nibabies/utils/debug.py
nibabies/utils/derivatives.py
nibabies/utils/filtering.py
nibabies/utils/misc.py
nibabies/utils/telemetry.py
nibabies/utils/transforms.py
nibabies/utils/viz.py
nibabies-25.2.1.dist-info/METADATA
nibabies-25.2.1.dist-info/WHEEL
nibabies-25.2.1.dist-info/entry_points.txt
nibabies-25.2.1.dist-info/licenses/LICENSE
nibabies-25.2.1.dist-info/RECORD
