Metadata-Version: 2.4
Name: nibabies
Version: 25.2.1
Summary: Processing workflows for magnetic resonance images of the brain in infants
Project-URL: Documentation, https://nibabies.readthedocs.io/en/latest/
Project-URL: Source Code, https://github.com/nipreps/nibabies
Project-URL: Bug Tracker, https://github.com/nipreps/nibabies/issues
Project-URL: Docker Images, https://hub.docker.com/r/nipreps/nibabies
Author-email: The NiPreps Developers <nipreps@gmail.com>
License:                                  Apache License
License-File: LICENSE
Classifier: Development Status :: 4 - Beta
Classifier: Intended Audience :: Science/Research
Classifier: License :: OSI Approved :: Apache Software License
Classifier: Programming Language :: Python :: 3.10
Classifier: Programming Language :: Python :: 3.11
Classifier: Programming Language :: Python :: 3.12
Classifier: Topic :: Scientific/Engineering :: Image Recognition
Requires-Python: >=3.10
Requires-Dist: acres
Requires-Dist: nibabel>=5.1.0
Requires-Dist: nipype>=1.9.0
Requires-Dist: nireports>=25.3.0
Requires-Dist: nitime
Requires-Dist: nitransforms>=25.0.1
Requires-Dist: niworkflows>=1.14.1
Requires-Dist: numpy>=2.0
Requires-Dist: packaging
Requires-Dist: pandas<3
Requires-Dist: psutil>=5.4
Requires-Dist: pybids>=0.15.0
Requires-Dist: requests
Requires-Dist: sdcflows>=2.14.0
Requires-Dist: smriprep>=0.19.1
Requires-Dist: tedana>=23.0.2
Requires-Dist: templateflow>=25.0.3
Requires-Dist: toml
Requires-Dist: typing-extensions; python_version < '3.11'
Provides-Extra: all
Requires-Dist: coverage[toml]; extra == 'all'
Requires-Dist: fuzzywuzzy; extra == 'all'
Requires-Dist: migas>=0.4.0; extra == 'all'
Requires-Dist: myst-parser; extra == 'all'
Requires-Dist: pre-commit; extra == 'all'
Requires-Dist: pydot>=1.2.3; extra == 'all'
Requires-Dist: pytest; extra == 'all'
Requires-Dist: pytest-cov; extra == 'all'
Requires-Dist: pytest-env; extra == 'all'
Requires-Dist: pytest-xdist; extra == 'all'
Requires-Dist: python-levenshtein; extra == 'all'
Requires-Dist: ruff; extra == 'all'
Requires-Dist: shibuya; extra == 'all'
Requires-Dist: sphinx-argparse; extra == 'all'
Requires-Dist: sphinx-togglebutton; extra == 'all'
Requires-Dist: sphinx>=1.8; extra == 'all'
Requires-Dist: sphinxcontrib-bibtex; extra == 'all'
Provides-Extra: container
Requires-Dist: datalad; extra == 'container'
Requires-Dist: datalad-osf; extra == 'container'
Requires-Dist: migas>=0.4.0; extra == 'container'
Provides-Extra: dev
Requires-Dist: pre-commit; extra == 'dev'
Requires-Dist: ruff; extra == 'dev'
Provides-Extra: doc
Requires-Dist: myst-parser; extra == 'doc'
Requires-Dist: pydot>=1.2.3; extra == 'doc'
Requires-Dist: shibuya; extra == 'doc'
Requires-Dist: sphinx-argparse; extra == 'doc'
Requires-Dist: sphinx-togglebutton; extra == 'doc'
Requires-Dist: sphinx>=1.8; extra == 'doc'
Requires-Dist: sphinxcontrib-bibtex; extra == 'doc'
Provides-Extra: docs
Requires-Dist: myst-parser; extra == 'docs'
Requires-Dist: pydot>=1.2.3; extra == 'docs'
Requires-Dist: shibuya; extra == 'docs'
Requires-Dist: sphinx-argparse; extra == 'docs'
Requires-Dist: sphinx-togglebutton; extra == 'docs'
Requires-Dist: sphinx>=1.8; extra == 'docs'
Requires-Dist: sphinxcontrib-bibtex; extra == 'docs'
Provides-Extra: duecredit
Requires-Dist: duecredit; extra == 'duecredit'
Provides-Extra: maint
Requires-Dist: fuzzywuzzy; extra == 'maint'
Requires-Dist: python-levenshtein; extra == 'maint'
Provides-Extra: telemetry
Requires-Dist: migas>=0.4.0; extra == 'telemetry'
Provides-Extra: test
Requires-Dist: coverage[toml]; extra == 'test'
Requires-Dist: pytest; extra == 'test'
Requires-Dist: pytest-cov; extra == 'test'
Requires-Dist: pytest-env; extra == 'test'
Requires-Dist: pytest-xdist; extra == 'test'
Provides-Extra: tests
Requires-Dist: coverage[toml]; extra == 'tests'
Requires-Dist: pytest; extra == 'tests'
Requires-Dist: pytest-cov; extra == 'tests'
Requires-Dist: pytest-env; extra == 'tests'
Requires-Dist: pytest-xdist; extra == 'tests'
